protozfits/Auxiliary_pb2.py
protozfits/CDTS_pb2.py
protozfits/CoreMessages_pb2.py
protozfits/DL0v1_Subarray_pb2.py
protozfits/DL0v1_Telescope_pb2.py
protozfits/DL0v1_Trigger_pb2.py
protozfits/ProtoDataModel_pb2.py
protozfits/ProtoR1_DigiCam_pb2.py
protozfits/ProtoR1_LSTCam_pb2.py
protozfits/ProtoR1_NectarCam_pb2.py
protozfits/ProtoR1_pb2.py
protozfits/R1v1_debug_pb2.py
protozfits/R1v1_pb2.py
protozfits/SAG_data_v1_pb2.py
protozfits/__init__.py
protozfits/_version.py
protozfits/anyarray.py
protozfits/libADHCore.so
protozfits/libZFitsIO.so
protozfits/rawzfits.cpython-313-x86_64-linux-gnu.so
protozfits/recompress_zfits.py
protozfits/version.py
protozfits/tests/__init__.py
protozfits/tests/test_1_rawzfits.py
protozfits/tests/test_cta_r1_dummy_file.py
protozfits/tests/test_file.py
protozfits/tests/test_ifits.py
protozfits/tests/test_multizfitsfiles.py
protozfits/tests/test_protozifits.py
protozfits/tests/test_protozofits.py
protozfits/tests/test_r1_example_file.py
protozfits/tests/test_recompress.py
protozfits/tests/resources/10_CTA_R1_dummy_evts.fits.fz
protozfits/tests/resources/example_100evts.fits.fz
protozfits/tests/resources/example_10evts.fits.fz
protozfits/tests/resources/example_9evts_NectarCAM.fits.fz
protozfits/tests/resources/example_LST_R1_10_evts.fits.fz
protozfits/tests/resources/example_SST1M_20180822.fits.fz
protozfits.libs/libabsl_bad_optional_access-c2967e71.so.2401.0.0
protozfits.libs/libabsl_bad_variant_access-a75dd677.so.2401.0.0
protozfits.libs/libabsl_base-0ed7cc38.so.2401.0.0
protozfits.libs/libabsl_city-0b01f118.so.2401.0.0
protozfits.libs/libabsl_civil_time-3713c875.so.2401.0.0
protozfits.libs/libabsl_cord-97e3ef84.so.2401.0.0
protozfits.libs/libabsl_cord_internal-75ad8966.so.2401.0.0
protozfits.libs/libabsl_cordz_functions-5a628932.so.2401.0.0
protozfits.libs/libabsl_cordz_handle-4f9ed78d.so.2401.0.0
protozfits.libs/libabsl_cordz_info-3b935e4c.so.2401.0.0
protozfits-2.8.1.dist-info/METADATA
protozfits-2.8.1.dist-info/WHEEL
protozfits-2.8.1.dist-info/RECORD
protozfits-2.8.1.dist-info/licenses/LICENSE
