Metadata-Version: 2.2
Name: protozfits
Version: 2.8.1
Summary: Python bindings for the protobuf zfits library
Maintainer-Email: Maximilian Linhoff <maximilian.linhoff@tu-dortmund.de>
License: BSD-3-Clause
Classifier: Development Status :: 4 - Beta
Classifier: Intended Audience :: Science/Research
Classifier: License :: OSI Approved :: BSD License
Classifier: Operating System :: MacOS
Classifier: Operating System :: POSIX :: Linux
Classifier: Programming Language :: Python :: 3 :: Only
Project-URL: repository, https://gitlab.cta-observatory.org/cta-computing/common/protozfits-python/
Requires-Python: >=3.9
Requires-Dist: numpy
Requires-Dist: protobuf
Requires-Dist: astropy
Requires-Dist: tqdm
Requires-Dist: pyyaml
Provides-Extra: tests
Requires-Dist: pytest; extra == "tests"
Requires-Dist: pytest-cov; extra == "tests"
Provides-Extra: doc
Requires-Dist: sphinx; extra == "doc"
Requires-Dist: numpydoc; extra == "doc"
Requires-Dist: ctao-sphinx-theme; extra == "doc"
Requires-Dist: sphinx-changelog; extra == "doc"
Requires-Dist: sphinx-automodapi; extra == "doc"
Provides-Extra: dev
Requires-Dist: sphinx-autobuild; extra == "dev"
Requires-Dist: towncrier; extra == "dev"
Provides-Extra: all
Requires-Dist: protozfits[dev,doc,tests]; extra == "all"
